Calculator/__init__.py
Calculator/add/__init__.py
Calculator/div/__init__.py
sample_calsi-0.0.1.dist-info/LICENSE
sample_calsi-0.0.1.dist-info/METADATA
sample_calsi-0.0.1.dist-info/WHEEL
sample_calsi-0.0.1.dist-info/top_level.txt
sample_calsi-0.0.1.dist-info/RECORD
